pf_bindings_python-0.1.1.dist-info/METADATA
pf_bindings_python-0.1.1.dist-info/WHEEL
pf_bindings_python/__init__.py
pf_bindings_python/pf_bindings_python.abi3.so
pf_bindings_python-0.1.1.dist-info/RECORD
