Metadata-Version: 2.4
Name: pf-bindings-python
Version: 0.1.1
Classifier: Programming Language :: Rust
Classifier: Programming Language :: Python :: Implementation :: CPython
Classifier: Programming Language :: Python :: Implementation :: PyPy
Summary: Python bindings for Probably Fair core library
Author: Probably Fair
License: Apache-2.0
Requires-Python: >=3.8
